cursebox/__init__.py
cursebox/lastfm.py
cursebox/lms.py
cursebox/v1.py
cursebox/v2.py
cursebox/version.py
cursebox/components/__init__.py
cursebox/components/main.py
cursebox/components/screen.py
cursebox/components/splash.py
cursebox/resources/logo.txt
cursebox/resources/logo2.txt
cursebox/resources/logo_3d_ascii.txt
cursebox/resources/logo_alpha.txt
cursebox/resources/logo_amc_neko.txt
cursebox/resources/logo_ansi_compact.txt
cursebox/resources/logo_banner3_d.txt
cursebox/resources/logo_big_ascii_9.txt
cursebox/resources/logo_blood.txt
cursebox/resources/logo_blur.txt
cursebox/resources/logo_braille.txt
cursebox/resources/logo_computer.txt
cursebox/resources/logo_doom.txt
cursebox/resources/logo_electronic.txt
cursebox/resources/logo_elite.txt
cursebox/resources/logo_emboss.txt
cursebox/resources/logo_graceful.txt
cursebox/resources/logo_graffiti.txt
cursebox/resources/logo_impossible.txt
cursebox/resources/logo_isometric.txt
cursebox/resources/logo_merlin.txt
cursebox/resources/logo_miniwi.txt
cursebox/resources/logo_rebel.txt
cursebox/resources/logo_shaded_blocky.txt
cursebox/resources/logo_slant.txt
cursebox/resources/logo_small.txt
cursebox/resources/logo_soft.txt
cursebox/resources/logo_sub_zero.txt
cursebox/resources/logo_terrace.txt
cursebox/resources/logo_tmplr.txt
cursebox-1.1.5.dist-info/licenses/LICENSE.txt
cursebox-1.1.5.dist-info/METADATA
cursebox-1.1.5.dist-info/WHEEL
cursebox-1.1.5.dist-info/entry_points.txt
cursebox-1.1.5.dist-info/top_level.txt
cursebox-1.1.5.dist-info/RECORD
