Metadata-Version: 2.4
Name: cursebox
Version: 1.1.5
Summary: A TUI for Lyrion Music Server. Squeezeboxes at your fingertips!
License-Expression: MIT
License-File: LICENSE.txt
Requires-Dist: telnetlib3==2.0.8
Dynamic: license-file
